MicrobeCensus_SourceApp-1.1.2.data/scripts/run_microbe_census.py
microbe_census/__init__.py
microbe_census/microbe_census.py
microbe_census/bin/prerapsearch_Darwin_2.15
microbe_census/bin/prerapsearch_Linux_2.15
microbe_census/bin/rapsearch_Darwin_2.15
microbe_census/bin/rapsearch_Linux_2.15
microbe_census/data/coefficients.map
microbe_census/data/gene_fam.map
microbe_census/data/gene_len.map
microbe_census/data/pars.map
microbe_census/data/rapdb_2.15
microbe_census/data/rapdb_2.15.info
microbe_census/data/read_len.map
microbe_census/data/weights.map
microbe_census/example/example.fa.gz
microbe_census/example/example.fq.gz
tests/__init__.py
tests/test_microbe_census.py
tests/data/community.txt
tests/data/metagenome.fa.gz
MicrobeCensus_SourceApp-1.1.2.dist-info/LICENSE.txt
MicrobeCensus_SourceApp-1.1.2.dist-info/METADATA
MicrobeCensus_SourceApp-1.1.2.dist-info/WHEEL
MicrobeCensus_SourceApp-1.1.2.dist-info/top_level.txt
MicrobeCensus_SourceApp-1.1.2.dist-info/RECORD
