Metadata-Version: 2.1
Name: MicrobeCensus-SourceApp
Version: 1.1.2
Summary: Estimation of average genome size from metagenomic data
Home-page: https://github.com/snayfach/MicrobeCensus
Author: Stephen Nayfach
Author-email: snayfach@gmail.com
License: GPL
License-File: LICENSE.txt
Requires-Dist: biopython
Requires-Dist: numpy
